lymphatic/__init__.py
lymphatic/lymphatic.r.html
lymphatic/studies.py
lymphatic/tutorial.r.html
lymphatic/cyte/_clique.py
lymphatic/cyte/create.py
lymphatic/cyte/cyte.r.html
lymphatic/cyte/drop.py
lymphatic/cyte/list.py
lymphatic/cyte/rename.py
lymphatic/cyte/rethinkdb/rethinkdb.r.html
lymphatic/cyte/rethinkdb/server_config/rename_server.py
lymphatic/immunity/connect.py
lymphatic/immunity/variables.py
lymphatic/molecule/__init__.py
lymphatic/molecule/insert.py
lymphatic/node/__init__.py
lymphatic/node/connect.py
lymphatic/node/multi.py
lymphatic/node/node.r.html
lymphatic/node/process.py
lymphatic/node/data/export.py
lymphatic/node/data/import.py
lymphatic/node/proxy/proxy.r.html
lymphatic/organelle/config.py
lymphatic/organelle/create.py
lymphatic/organelle/list.py
lymphatic/organelle/reconfigure.py
lymphatic/organelle/rename.py
lymphatic/organelle/primary_index/__init__.py
lymphatic/organelle/primary_index/primary_index.r.html
lymphatic/organelle/secondary_index/lymphatic.r.html
lymphatic/system/__init__.py
lymphatic/system/cannot_connect.py
lymphatic/system/climate.py
lymphatic/system/connect.py
lymphatic/system/start.py
lymphatic/system/system.r.html
lymphatic-0.0.12.dist-info/METADATA
lymphatic-0.0.12.dist-info/WHEEL
lymphatic-0.0.12.dist-info/entry_points.txt
lymphatic-0.0.12.dist-info/top_level.txt
lymphatic-0.0.12.dist-info/RECORD
