Metadata-Version: 2.1
Name: lymphatic
Version: 0.0.12
Summary: The cybernetic immune system hyper drive of the inter-ellipitic jumper.
Requires-Dist: rethinkdb
Requires-Dist: botanical
